LICENSE
MANIFEST.in
README.rst
requirements.txt
setup.cfg
setup.py
django_auth_fogbugz/__init__.py
django_auth_fogbugz/backend.py
django_auth_fogbugz/django_auth_fogbugz_settings.py
django_auth_fogbugz/models.py
django_auth_fogbugz/tests.py
django_auth_fogbugz.egg-info/PKG-INFO
django_auth_fogbugz.egg-info/SOURCES.txt
django_auth_fogbugz.egg-info/dependency_links.txt
django_auth_fogbugz.egg-info/requires.txt
django_auth_fogbugz.egg-info/top_level.txt
docs/Makefile
docs/conf.py
docs/index.rst