Metadata-Version: 1.1
Name: django-auth-fogbugz
Version: 1.1.0
Summary: Django FogBugz authentication backend
Home-page: https://github.com/dougn/django-auth-fogbugz/
Author: Doug Napoleone
Author-email: doug.napoleone+django-auth-fogbugz@gmail.com
License: BSD
Keywords: django,fogbugz,authentication,auth
Platform: UNKNOWN
Classifier: Development Status :: 5 - Production/Stable
Classifier: Environment :: Web Environment
Classifier: Programming Language :: Python
Classifier: Programming Language :: Python :: 2.5
Classifier: Programming Language :: Python :: 2.6
Classifier: Programming Language :: Python :: 2.7
Classifier: Framework :: Django
Classifier: Intended Audience :: Developers
Classifier: Intended Audience :: System Administrators
Classifier: License :: OSI Approved :: BSD License
Classifier: Topic :: Internet :: WWW/HTTP
Classifier: Topic :: System :: Systems Administration :: Authentication/Directory
Classifier: Topic :: Software Development :: Libraries :: Python Modules
